adverse_event_app/__init__.py
adverse_event_app/action_items.py
adverse_event_app/admin.py
adverse_event_app/apps.py
adverse_event_app/baker_recipes.py
adverse_event_app/consents.py
adverse_event_app/list_data.py
adverse_event_app/models.py
adverse_event_app/visit_schedules.py
adverse_event_app-1.0.3.dist-info/licenses/AUTHORS
adverse_event_app-1.0.3.dist-info/licenses/LICENSE
adverse_event_app-1.0.3.dist-info/METADATA
adverse_event_app-1.0.3.dist-info/WHEEL
adverse_event_app-1.0.3.dist-info/top_level.txt
adverse_event_app-1.0.3.dist-info/RECORD
