Metadata-Version: 2.4
Name: adverse-event-app
Version: 1.0.3
Summary: Add your description here
Requires-Python: >=3.13
License-File: LICENSE
License-File: AUTHORS
Dynamic: license-file
